{
	"backtrace" : 0,
	"backtraceGraph" : 
	{
		"commands" : [],
		"files" : 
		[
			"generators/chm/CMakeLists.txt"
		],
		"nodes" : 
		[
			{
				"file" : 0
			}
		]
	},
	"dependencies" : 
	[
		{
			"id" : "chmgeneratortest_autogen_timestamp_deps::@62e0aaccda60e32405cc"
		}
	],
	"id" : "chmgeneratortest_autogen::@62e0aaccda60e32405cc",
	"isGeneratorProvided" : true,
	"name" : "chmgeneratortest_autogen",
	"paths" : 
	{
		"build" : "generators/chm",
		"source" : "generators/chm"
	},
	"sourceGroups" : 
	[
		{
			"name" : "",
			"sourceIndexes" : 
			[
				0
			]
		},
		{
			"name" : "CMake Rules",
			"sourceIndexes" : 
			[
				1,
				2
			]
		}
	],
	"sources" : 
	[
		{
			"backtrace" : 0,
			"isGenerated" : true,
			"path" : "/home/szybet/kdesrc/kde/kdegraphics/build-okular-Desktop-RelWithDebInfo/generators/chm/CMakeFiles/chmgeneratortest_autogen",
			"sourceGroupIndex" : 0
		},
		{
			"backtrace" : 0,
			"isGenerated" : true,
			"path" : "/home/szybet/kdesrc/kde/kdegraphics/build-okular-Desktop-RelWithDebInfo/generators/chm/CMakeFiles/chmgeneratortest_autogen.rule",
			"sourceGroupIndex" : 1
		},
		{
			"backtrace" : 0,
			"isGenerated" : true,
			"path" : "/home/szybet/kdesrc/kde/kdegraphics/build-okular-Desktop-RelWithDebInfo/generators/chm/chmgeneratortest_autogen/timestamp.rule",
			"sourceGroupIndex" : 1
		}
	],
	"type" : "UTILITY"
}
