{
	"artifacts" : 
	[
		{
			"path" : "bin/plugins/okular/okularGenerator_dvi.so"
		}
	],
	"backtrace" : 3,
	"backtraceGraph" : 
	{
		"commands" : 
		[
			"add_library",
			"kcoreaddons_add_plugin",
			"okular_add_generator",
			"install",
			"target_link_libraries",
			"set_target_properties",
			"include",
			"find_package",
			"find_dependency",
			"add_definitions",
			"remove_definitions",
			"target_compile_definitions",
			"include_directories"
		],
		"files" : 
		[
			"/home/build/inkbox/compiled-binaries/arm-kobo-linux-gnueabihf/arm-kobo-linux-gnueabihf/sysroot/lib/cmake/KF5CoreAddons/KF5CoreAddonsMacros.cmake",
			"generators/CMakeLists.txt",
			"generators/dvi/CMakeLists.txt",
			"CMakeLists.txt",
			"/home/build/inkbox/compiled-binaries/arm-kobo-linux-gnueabihf/arm-kobo-linux-gnueabihf/sysroot/lib/cmake/KF5XmlGui/KF5XmlGuiTargets.cmake",
			"/home/build/inkbox/compiled-binaries/arm-kobo-linux-gnueabihf/arm-kobo-linux-gnueabihf/sysroot/lib/cmake/KF5XmlGui/KF5XmlGuiConfig.cmake",
			"/usr/share/cmake/Modules/CMakeFindDependencyMacro.cmake",
			"/home/build/inkbox/compiled-binaries/arm-kobo-linux-gnueabihf/arm-kobo-linux-gnueabihf/sysroot/lib/cmake/KF5KIO/KF5KIOConfig.cmake",
			"/home/build/inkbox/compiled-binaries/arm-kobo-linux-gnueabihf/arm-kobo-linux-gnueabihf/sysroot/share/ECM/find-modules/FindKF5.cmake",
			"/home/build/inkbox/compiled-binaries/arm-kobo-linux-gnueabihf/arm-kobo-linux-gnueabihf/sysroot/lib/cmake/KF5ConfigWidgets/KF5ConfigWidgetsTargets.cmake",
			"/home/build/inkbox/compiled-binaries/arm-kobo-linux-gnueabihf/arm-kobo-linux-gnueabihf/sysroot/lib/cmake/KF5ConfigWidgets/KF5ConfigWidgetsConfig.cmake",
			"/home/build/inkbox/compiled-binaries/arm-kobo-linux-gnueabihf/arm-kobo-linux-gnueabihf/sysroot/lib/cmake/KF5Auth/KF5AuthTargets.cmake",
			"/home/build/inkbox/compiled-binaries/arm-kobo-linux-gnueabihf/arm-kobo-linux-gnueabihf/sysroot/lib/cmake/KF5Auth/KF5AuthConfig.cmake",
			"/home/build/inkbox/compiled-binaries/arm-kobo-linux-gnueabihf/arm-kobo-linux-gnueabihf/sysroot/lib/cmake/KF5Config/KF5ConfigTargets.cmake",
			"/home/build/inkbox/compiled-binaries/arm-kobo-linux-gnueabihf/arm-kobo-linux-gnueabihf/sysroot/lib/cmake/KF5Config/KF5ConfigConfig.cmake",
			"/home/build/inkbox/compiled-binaries/arm-kobo-linux-gnueabihf/arm-kobo-linux-gnueabihf/sysroot/lib/cmake/KF5I18n/KF5I18nTargets.cmake",
			"/home/build/inkbox/compiled-binaries/arm-kobo-linux-gnueabihf/arm-kobo-linux-gnueabihf/sysroot/lib/cmake/KF5I18n/KF5I18nConfig.cmake"
		],
		"nodes" : 
		[
			{
				"file" : 2
			},
			{
				"command" : 2,
				"file" : 2,
				"line" : 46,
				"parent" : 0
			},
			{
				"command" : 1,
				"file" : 1,
				"line" : 3,
				"parent" : 1
			},
			{
				"command" : 0,
				"file" : 0,
				"line" : 186,
				"parent" : 2
			},
			{
				"command" : 3,
				"file" : 0,
				"line" : 219,
				"parent" : 2
			},
			{
				"command" : 4,
				"file" : 2,
				"line" : 48,
				"parent" : 0
			},
			{
				"command" : 4,
				"file" : 2,
				"line" : 50,
				"parent" : 0
			},
			{
				"file" : 3
			},
			{
				"command" : 4,
				"file" : 3,
				"line" : 429,
				"parent" : 7
			},
			{
				"command" : 7,
				"file" : 3,
				"line" : 118,
				"parent" : 7
			},
			{
				"file" : 8,
				"parent" : 9
			},
			{
				"command" : 7,
				"file" : 8,
				"line" : 52,
				"parent" : 10
			},
			{
				"file" : 7,
				"parent" : 11
			},
			{
				"command" : 8,
				"file" : 7,
				"line" : 43,
				"parent" : 12
			},
			{
				"command" : 7,
				"file" : 6,
				"line" : 76,
				"parent" : 13
			},
			{
				"file" : 5,
				"parent" : 14
			},
			{
				"command" : 6,
				"file" : 5,
				"line" : 55,
				"parent" : 15
			},
			{
				"file" : 4,
				"parent" : 16
			},
			{
				"command" : 5,
				"file" : 4,
				"line" : 61,
				"parent" : 17
			},
			{
				"command" : 7,
				"file" : 8,
				"line" : 52,
				"parent" : 10
			},
			{
				"file" : 10,
				"parent" : 19
			},
			{
				"command" : 6,
				"file" : 10,
				"line" : 54,
				"parent" : 20
			},
			{
				"file" : 9,
				"parent" : 21
			},
			{
				"command" : 5,
				"file" : 9,
				"line" : 61,
				"parent" : 22
			},
			{
				"command" : 8,
				"file" : 10,
				"line" : 29,
				"parent" : 20
			},
			{
				"command" : 7,
				"file" : 6,
				"line" : 76,
				"parent" : 24
			},
			{
				"file" : 12,
				"parent" : 25
			},
			{
				"command" : 6,
				"file" : 12,
				"line" : 55,
				"parent" : 26
			},
			{
				"file" : 11,
				"parent" : 27
			},
			{
				"command" : 5,
				"file" : 11,
				"line" : 69,
				"parent" : 28
			},
			{
				"command" : 7,
				"file" : 8,
				"line" : 52,
				"parent" : 10
			},
			{
				"file" : 14,
				"parent" : 30
			},
			{
				"command" : 6,
				"file" : 14,
				"line" : 29,
				"parent" : 31
			},
			{
				"file" : 13,
				"parent" : 32
			},
			{
				"command" : 5,
				"file" : 13,
				"line" : 69,
				"parent" : 33
			},
			{
				"command" : 7,
				"file" : 8,
				"line" : 52,
				"parent" : 10
			},
			{
				"file" : 16,
				"parent" : 35
			},
			{
				"command" : 6,
				"file" : 16,
				"line" : 34,
				"parent" : 36
			},
			{
				"file" : 15,
				"parent" : 37
			},
			{
				"command" : 5,
				"file" : 15,
				"line" : 61,
				"parent" : 38
			},
			{
				"command" : 9,
				"file" : 2,
				"line" : 7,
				"parent" : 0
			},
			{
				"command" : 10,
				"file" : 2,
				"line" : 1,
				"parent" : 0
			},
			{
				"command" : 11,
				"file" : 0,
				"line" : 197,
				"parent" : 2
			},
			{
				"command" : 9,
				"file" : 2,
				"line" : 2,
				"parent" : 0
			},
			{
				"command" : 12,
				"file" : 3,
				"line" : 281,
				"parent" : 7
			}
		]
	},
	"compileGroups" : 
	[
		{
			"compileCommandFragments" : 
			[
				{
					"fragment" : " -fno-operator-names -fno-exceptions -Wall -Wextra -Wcast-align -Wchar-subscripts -Wformat-security -Wno-long-long -Wpointer-arith -Wundef -Wnon-virtual-dtor -Woverloaded-virtual -Werror=return-type -Werror=init-self -Wvla -Wdate-time -Wsuggest-override -Wlogical-op -pedantic -Wzero-as-null-pointer-constant -Wmissing-include-dirs -g -std=c++17 -fPIC -fvisibility=hidden -fvisibility-inlines-hidden"
				},
				{
					"backtrace" : 5,
					"fragment" : "-fPIC"
				}
			],
			"defines" : 
			[
				{
					"backtrace" : 40,
					"define" : "HAVE_FREETYPE"
				},
				{
					"backtrace" : 5,
					"define" : "KCOREADDONS_LIB"
				},
				{
					"backtrace" : 41,
					"define" : "KF_DEPRECATED_WARNINGS_SINCE=0x055C00"
				},
				{
					"backtrace" : 42,
					"define" : "KPLUGINFACTORY_PLUGIN_CLASS_INTERNAL_NAME=okularGenerator_dvi_factory"
				},
				{
					"backtrace" : 5,
					"define" : "QT_CORE_LIB"
				},
				{
					"backtrace" : 5,
					"define" : "QT_DBUS_LIB"
				},
				{
					"backtrace" : 41,
					"define" : "QT_DEPRECATED_WARNINGS_SINCE=0x050F02"
				},
				{
					"backtrace" : 5,
					"define" : "QT_GUI_LIB"
				},
				{
					"backtrace" : 41,
					"define" : "QT_NO_CAST_FROM_ASCII"
				},
				{
					"backtrace" : 41,
					"define" : "QT_NO_CAST_FROM_BYTEARRAY"
				},
				{
					"backtrace" : 41,
					"define" : "QT_NO_CAST_TO_ASCII"
				},
				{
					"backtrace" : 41,
					"define" : "QT_NO_FOREACH"
				},
				{
					"backtrace" : 41,
					"define" : "QT_NO_KEYWORDS"
				},
				{
					"backtrace" : 41,
					"define" : "QT_NO_NARROWING_CONVERSIONS_IN_CONNECT"
				},
				{
					"backtrace" : 41,
					"define" : "QT_NO_URL_CAST_FROM_STRING"
				},
				{
					"backtrace" : 5,
					"define" : "QT_PRINTSUPPORT_LIB"
				},
				{
					"backtrace" : 41,
					"define" : "QT_STRICT_ITERATORS"
				},
				{
					"backtrace" : 41,
					"define" : "QT_USE_QSTRINGBUILDER"
				},
				{
					"backtrace" : 5,
					"define" : "QT_WIDGETS_LIB"
				},
				{
					"backtrace" : 5,
					"define" : "QT_XML_LIB"
				},
				{
					"backtrace" : 43,
					"define" : "TRANSLATION_DOMAIN=\"okular_dvi\""
				},
				{
					"backtrace" : 41,
					"define" : "_FILE_OFFSET_BITS=64"
				},
				{
					"backtrace" : 41,
					"define" : "_GNU_SOURCE"
				},
				{
					"backtrace" : 41,
					"define" : "_LARGEFILE64_SOURCE"
				},
				{
					"define" : "okularGenerator_dvi_EXPORTS"
				}
			],
			"includes" : 
			[
				{
					"path" : "/home/szybet/kdesrc/kde/kdegraphics/build-okular-Kobo-Debug/generators/dvi"
				},
				{
					"path" : "/home/szybet/kdesrc/kde/kdegraphics/okular/generators/dvi"
				},
				{
					"backtrace" : 0,
					"path" : "/home/szybet/kdesrc/kde/kdegraphics/build-okular-Kobo-Debug/generators/dvi/okularGenerator_dvi_autogen/include"
				},
				{
					"backtrace" : 44,
					"path" : "/home/szybet/kdesrc/kde/kdegraphics/okular"
				},
				{
					"backtrace" : 44,
					"path" : "/home/szybet/kdesrc/kde/kdegraphics/okular/core/synctex"
				},
				{
					"backtrace" : 44,
					"path" : "/home/szybet/kdesrc/kde/kdegraphics/build-okular-Kobo-Debug/core"
				},
				{
					"backtrace" : 5,
					"path" : "/home/szybet/kdesrc/kde/kdegraphics/build-okular-Kobo-Debug"
				},
				{
					"backtrace" : 44,
					"path" : "/home/build/inkbox/compiled-binaries/arm-kobo-linux-gnueabihf/arm-kobo-linux-gnueabihf/sysroot/include/phonon4qt5"
				},
				{
					"backtrace" : 44,
					"path" : "/home/build/inkbox/compiled-binaries/arm-kobo-linux-gnueabihf/arm-kobo-linux-gnueabihf/sysroot/include/phonon4qt5/KDE"
				},
				{
					"backtrace" : 5,
					"isSystem" : true,
					"path" : "/home/build/inkbox/compiled-binaries/arm-kobo-linux-gnueabihf/arm-kobo-linux-gnueabihf/sysroot/include/KF5/KCoreAddons"
				},
				{
					"backtrace" : 5,
					"isSystem" : true,
					"path" : "/home/build/inkbox/compiled-binaries/arm-kobo-linux-gnueabihf/arm-kobo-linux-gnueabihf/sysroot/include/KF5"
				},
				{
					"backtrace" : 5,
					"isSystem" : true,
					"path" : "/home/build/inkbox/compiled-binaries/arm-kobo-linux-gnueabihf/arm-kobo-linux-gnueabihf/sysroot/include"
				},
				{
					"backtrace" : 5,
					"isSystem" : true,
					"path" : "/home/build/inkbox/compiled-binaries/arm-kobo-linux-gnueabihf/arm-kobo-linux-gnueabihf/sysroot/include/QtCore"
				},
				{
					"backtrace" : 5,
					"isSystem" : true,
					"path" : "/home/build/inkbox/compiled-binaries/arm-kobo-linux-gnueabihf/arm-kobo-linux-gnueabihf/sysroot/./mkspecs/linux-kobo-gnueabihf-g++"
				},
				{
					"backtrace" : 5,
					"isSystem" : true,
					"path" : "/home/build/inkbox/compiled-binaries/arm-kobo-linux-gnueabihf/arm-kobo-linux-gnueabihf/sysroot/include/KF5/KXmlGui"
				},
				{
					"backtrace" : 5,
					"isSystem" : true,
					"path" : "/home/build/inkbox/compiled-binaries/arm-kobo-linux-gnueabihf/arm-kobo-linux-gnueabihf/sysroot/include/QtXml"
				},
				{
					"backtrace" : 5,
					"isSystem" : true,
					"path" : "/home/build/inkbox/compiled-binaries/arm-kobo-linux-gnueabihf/arm-kobo-linux-gnueabihf/sysroot/include/QtWidgets"
				},
				{
					"backtrace" : 5,
					"isSystem" : true,
					"path" : "/home/build/inkbox/compiled-binaries/arm-kobo-linux-gnueabihf/arm-kobo-linux-gnueabihf/sysroot/include/QtGui"
				},
				{
					"backtrace" : 5,
					"isSystem" : true,
					"path" : "/home/build/inkbox/compiled-binaries/arm-kobo-linux-gnueabihf/arm-kobo-linux-gnueabihf/sysroot/include/KF5/KConfig"
				},
				{
					"backtrace" : 5,
					"isSystem" : true,
					"path" : "/home/build/inkbox/compiled-binaries/arm-kobo-linux-gnueabihf/arm-kobo-linux-gnueabihf/sysroot/include/KF5/KConfigCore"
				},
				{
					"backtrace" : 5,
					"isSystem" : true,
					"path" : "/home/build/inkbox/compiled-binaries/arm-kobo-linux-gnueabihf/arm-kobo-linux-gnueabihf/sysroot/include/KF5/KConfigWidgets"
				},
				{
					"backtrace" : 5,
					"isSystem" : true,
					"path" : "/home/build/inkbox/compiled-binaries/arm-kobo-linux-gnueabihf/arm-kobo-linux-gnueabihf/sysroot/include/KF5/KWidgetsAddons"
				},
				{
					"backtrace" : 5,
					"isSystem" : true,
					"path" : "/home/build/inkbox/compiled-binaries/arm-kobo-linux-gnueabihf/arm-kobo-linux-gnueabihf/sysroot/include/KF5/KConfigGui"
				},
				{
					"backtrace" : 5,
					"isSystem" : true,
					"path" : "/home/build/inkbox/compiled-binaries/arm-kobo-linux-gnueabihf/arm-kobo-linux-gnueabihf/sysroot/include/KF5/KCodecs"
				},
				{
					"backtrace" : 5,
					"isSystem" : true,
					"path" : "/home/build/inkbox/compiled-binaries/arm-kobo-linux-gnueabihf/arm-kobo-linux-gnueabihf/sysroot/include/KF5/KAuthWidgets"
				},
				{
					"backtrace" : 5,
					"isSystem" : true,
					"path" : "/home/build/inkbox/compiled-binaries/arm-kobo-linux-gnueabihf/arm-kobo-linux-gnueabihf/sysroot/include/KF5/KAuthCore"
				},
				{
					"backtrace" : 5,
					"isSystem" : true,
					"path" : "/home/build/inkbox/compiled-binaries/arm-kobo-linux-gnueabihf/arm-kobo-linux-gnueabihf/sysroot/include/KF5/KAuth"
				},
				{
					"backtrace" : 5,
					"isSystem" : true,
					"path" : "/home/build/inkbox/compiled-binaries/arm-kobo-linux-gnueabihf/arm-kobo-linux-gnueabihf/sysroot/include/QtDBus"
				},
				{
					"backtrace" : 5,
					"isSystem" : true,
					"path" : "/home/build/inkbox/compiled-binaries/arm-kobo-linux-gnueabihf/arm-kobo-linux-gnueabihf/sysroot/include/QtPrintSupport"
				},
				{
					"backtrace" : 5,
					"isSystem" : true,
					"path" : "/home/build/inkbox/compiled-binaries/arm-kobo-linux-gnueabihf/arm-kobo-linux-gnueabihf/sysroot/include/QtCore/5.15.2"
				},
				{
					"backtrace" : 5,
					"isSystem" : true,
					"path" : "/home/build/inkbox/compiled-binaries/arm-kobo-linux-gnueabihf/arm-kobo-linux-gnueabihf/sysroot/include/QtCore/5.15.2/QtCore"
				},
				{
					"backtrace" : 5,
					"isSystem" : true,
					"path" : "/home/build/inkbox/compiled-binaries/arm-kobo-linux-gnueabihf/arm-kobo-linux-gnueabihf/sysroot/include/KF5/KI18n"
				},
				{
					"backtrace" : 6,
					"isSystem" : true,
					"path" : "/home/build/inkbox/compiled-binaries/arm-kobo-linux-gnueabihf/arm-kobo-linux-gnueabihf/sysroot/include/freetype2"
				}
			],
			"language" : "CXX",
			"languageStandard" : 
			{
				"backtraces" : 
				[
					5
				],
				"standard" : "17"
			},
			"sourceIndexes" : 
			[
				0,
				1,
				2,
				3,
				4,
				5,
				6,
				7,
				8,
				9,
				10,
				11,
				12,
				13,
				14,
				15,
				16,
				17,
				18,
				19,
				20,
				21,
				22,
				23,
				24,
				25,
				26,
				27
			],
			"sysroot" : 
			{
				"path" : "/home/build/inkbox/compiled-binaries/arm-kobo-linux-gnueabihf/arm-kobo-linux-gnueabihf/sysroot"
			}
		}
	],
	"dependencies" : 
	[
		{
			"backtrace" : 5,
			"id" : "okularcore::@6890427a1f51a3e7e1df"
		},
		{
			"backtrace" : 0,
			"id" : "okularGenerator_dvi_autogen::@239122a401f324a2a715"
		}
	],
	"id" : "okularGenerator_dvi::@239122a401f324a2a715",
	"install" : 
	{
		"destinations" : 
		[
			{
				"backtrace" : 4,
				"path" : "lib/plugins/okular/generators"
			}
		],
		"prefix" : 
		{
			"path" : "/home/build/inkbox/compiled-binaries/arm-kobo-linux-gnueabihf/arm-kobo-linux-gnueabihf/sysroot"
		}
	},
	"link" : 
	{
		"commandFragments" : 
		[
			{
				"fragment" : "-Wl,--no-undefined -Wl,--fatal-warnings -Wl,--enable-new-dtags",
				"role" : "flags"
			},
			{
				"fragment" : "-Wl,-rpath,/home/szybet/kdesrc/kde/kdegraphics/build-okular-Kobo-Debug/bin:",
				"role" : "libraries"
			},
			{
				"backtrace" : 5,
				"fragment" : "../../bin/libOkular5Core.so.10.0.0",
				"role" : "libraries"
			},
			{
				"backtrace" : 6,
				"fragment" : "/home/build/inkbox/compiled-binaries/arm-kobo-linux-gnueabihf/arm-kobo-linux-gnueabihf/sysroot/lib/libfreetype.so",
				"role" : "libraries"
			},
			{
				"backtrace" : 8,
				"fragment" : "/home/build/inkbox/compiled-binaries/arm-kobo-linux-gnueabihf/arm-kobo-linux-gnueabihf/sysroot/lib/libKF5XmlGui.so.5.107.0",
				"role" : "libraries"
			},
			{
				"backtrace" : 8,
				"fragment" : "/home/build/inkbox/compiled-binaries/arm-kobo-linux-gnueabihf/arm-kobo-linux-gnueabihf/sysroot/lib/libQt5PrintSupport.so.5.15.2",
				"role" : "libraries"
			},
			{
				"backtrace" : 18,
				"fragment" : "/home/build/inkbox/compiled-binaries/arm-kobo-linux-gnueabihf/arm-kobo-linux-gnueabihf/sysroot/lib/libKF5ConfigWidgets.so.5.107.0",
				"role" : "libraries"
			},
			{
				"backtrace" : 5,
				"fragment" : "/home/build/inkbox/compiled-binaries/arm-kobo-linux-gnueabihf/arm-kobo-linux-gnueabihf/sysroot/lib/libKF5I18n.so.5.107.0",
				"role" : "libraries"
			},
			{
				"backtrace" : 8,
				"fragment" : "/home/build/inkbox/compiled-binaries/arm-kobo-linux-gnueabihf/arm-kobo-linux-gnueabihf/sysroot/lib/libKF5ConfigGui.so.5.107.0",
				"role" : "libraries"
			},
			{
				"backtrace" : 18,
				"fragment" : "/home/build/inkbox/compiled-binaries/arm-kobo-linux-gnueabihf/arm-kobo-linux-gnueabihf/sysroot/lib/libQt5Xml.so.5.15.2",
				"role" : "libraries"
			},
			{
				"backtrace" : 18,
				"fragment" : "/home/build/inkbox/compiled-binaries/arm-kobo-linux-gnueabihf/arm-kobo-linux-gnueabihf/sysroot/lib/libKF5ConfigCore.so.5.107.0",
				"role" : "libraries"
			},
			{
				"backtrace" : 23,
				"fragment" : "/home/build/inkbox/compiled-binaries/arm-kobo-linux-gnueabihf/arm-kobo-linux-gnueabihf/sysroot/lib/libKF5Auth.so.5.107.0",
				"role" : "libraries"
			},
			{
				"backtrace" : 29,
				"fragment" : "/home/build/inkbox/compiled-binaries/arm-kobo-linux-gnueabihf/arm-kobo-linux-gnueabihf/sysroot/lib/libKF5AuthCore.so.5.107.0",
				"role" : "libraries"
			},
			{
				"backtrace" : 8,
				"fragment" : "/home/build/inkbox/compiled-binaries/arm-kobo-linux-gnueabihf/arm-kobo-linux-gnueabihf/sysroot/lib/libKF5CoreAddons.so.5.107.0",
				"role" : "libraries"
			},
			{
				"backtrace" : 18,
				"fragment" : "/home/build/inkbox/compiled-binaries/arm-kobo-linux-gnueabihf/arm-kobo-linux-gnueabihf/sysroot/lib/libQt5DBus.so.5.15.2",
				"role" : "libraries"
			},
			{
				"backtrace" : 23,
				"fragment" : "/home/build/inkbox/compiled-binaries/arm-kobo-linux-gnueabihf/arm-kobo-linux-gnueabihf/sysroot/lib/libKF5WidgetsAddons.so.5.107.0",
				"role" : "libraries"
			},
			{
				"backtrace" : 23,
				"fragment" : "/home/build/inkbox/compiled-binaries/arm-kobo-linux-gnueabihf/arm-kobo-linux-gnueabihf/sysroot/lib/libKF5Codecs.so.5.107.0",
				"role" : "libraries"
			},
			{
				"backtrace" : 8,
				"fragment" : "/home/build/inkbox/compiled-binaries/arm-kobo-linux-gnueabihf/arm-kobo-linux-gnueabihf/sysroot/lib/libQt5Widgets.so.5.15.2",
				"role" : "libraries"
			},
			{
				"backtrace" : 34,
				"fragment" : "/home/build/inkbox/compiled-binaries/arm-kobo-linux-gnueabihf/arm-kobo-linux-gnueabihf/sysroot/lib/libQt5Gui.so.5.15.2",
				"role" : "libraries"
			},
			{
				"backtrace" : 39,
				"fragment" : "/home/build/inkbox/compiled-binaries/arm-kobo-linux-gnueabihf/arm-kobo-linux-gnueabihf/sysroot/lib/libQt5Core.so.5.15.2",
				"role" : "libraries"
			}
		],
		"language" : "CXX",
		"sysroot" : 
		{
			"path" : "/home/build/inkbox/compiled-binaries/arm-kobo-linux-gnueabihf/arm-kobo-linux-gnueabihf/sysroot"
		}
	},
	"name" : "okularGenerator_dvi",
	"nameOnDisk" : "okularGenerator_dvi.so",
	"paths" : 
	{
		"build" : "generators/dvi",
		"source" : "generators/dvi"
	},
	"sourceGroups" : 
	[
		{
			"name" : "Source Files",
			"sourceIndexes" : 
			[
				0,
				1,
				2,
				3,
				4,
				5,
				6,
				7,
				8,
				9,
				10,
				11,
				12,
				13,
				14,
				15,
				16,
				17,
				18,
				19,
				20,
				21,
				22,
				23,
				24,
				25,
				26,
				27
			]
		}
	],
	"sources" : 
	[
		{
			"backtrace" : 0,
			"compileGroupIndex" : 0,
			"isGenerated" : true,
			"path" : "/home/szybet/kdesrc/kde/kdegraphics/build-okular-Kobo-Debug/generators/dvi/okularGenerator_dvi_autogen/mocs_compilation.cpp",
			"sourceGroupIndex" : 0
		},
		{
			"backtrace" : 3,
			"compileGroupIndex" : 0,
			"path" : "generators/dvi/generator_dvi.cpp",
			"sourceGroupIndex" : 0
		},
		{
			"backtrace" : 3,
			"compileGroupIndex" : 0,
			"path" : "generators/dvi/bigEndianByteReader.cpp",
			"sourceGroupIndex" : 0
		},
		{
			"backtrace" : 3,
			"compileGroupIndex" : 0,
			"path" : "generators/dvi/dviRenderer.cpp",
			"sourceGroupIndex" : 0
		},
		{
			"backtrace" : 3,
			"compileGroupIndex" : 0,
			"path" : "generators/dvi/dviRenderer_draw.cpp",
			"sourceGroupIndex" : 0
		},
		{
			"backtrace" : 3,
			"compileGroupIndex" : 0,
			"path" : "generators/dvi/dviRenderer_prescan.cpp",
			"sourceGroupIndex" : 0
		},
		{
			"backtrace" : 3,
			"compileGroupIndex" : 0,
			"path" : "generators/dvi/dviRenderer_dr.cpp",
			"sourceGroupIndex" : 0
		},
		{
			"backtrace" : 3,
			"compileGroupIndex" : 0,
			"path" : "generators/dvi/special.cpp",
			"sourceGroupIndex" : 0
		},
		{
			"backtrace" : 3,
			"compileGroupIndex" : 0,
			"path" : "generators/dvi/dviFile.cpp",
			"sourceGroupIndex" : 0
		},
		{
			"backtrace" : 3,
			"compileGroupIndex" : 0,
			"path" : "generators/dvi/dviPageInfo.cpp",
			"sourceGroupIndex" : 0
		},
		{
			"backtrace" : 3,
			"compileGroupIndex" : 0,
			"path" : "generators/dvi/psgs.cpp",
			"sourceGroupIndex" : 0
		},
		{
			"backtrace" : 3,
			"compileGroupIndex" : 0,
			"path" : "generators/dvi/glyph.cpp",
			"sourceGroupIndex" : 0
		},
		{
			"backtrace" : 3,
			"compileGroupIndex" : 0,
			"path" : "generators/dvi/TeXFont.cpp",
			"sourceGroupIndex" : 0
		},
		{
			"backtrace" : 3,
			"compileGroupIndex" : 0,
			"path" : "generators/dvi/TeXFontDefinition.cpp",
			"sourceGroupIndex" : 0
		},
		{
			"backtrace" : 3,
			"compileGroupIndex" : 0,
			"path" : "generators/dvi/vf.cpp",
			"sourceGroupIndex" : 0
		},
		{
			"backtrace" : 3,
			"compileGroupIndex" : 0,
			"path" : "generators/dvi/TeXFont_PFB.cpp",
			"sourceGroupIndex" : 0
		},
		{
			"backtrace" : 3,
			"compileGroupIndex" : 0,
			"path" : "generators/dvi/TeXFont_PK.cpp",
			"sourceGroupIndex" : 0
		},
		{
			"backtrace" : 3,
			"compileGroupIndex" : 0,
			"path" : "generators/dvi/TeXFont_TFM.cpp",
			"sourceGroupIndex" : 0
		},
		{
			"backtrace" : 3,
			"compileGroupIndex" : 0,
			"path" : "generators/dvi/util.cpp",
			"sourceGroupIndex" : 0
		},
		{
			"backtrace" : 3,
			"compileGroupIndex" : 0,
			"path" : "generators/dvi/pageSize.cpp",
			"sourceGroupIndex" : 0
		},
		{
			"backtrace" : 3,
			"compileGroupIndex" : 0,
			"path" : "generators/dvi/simplePageSize.cpp",
			"sourceGroupIndex" : 0
		},
		{
			"backtrace" : 3,
			"compileGroupIndex" : 0,
			"path" : "generators/dvi/length.cpp",
			"sourceGroupIndex" : 0
		},
		{
			"backtrace" : 3,
			"compileGroupIndex" : 0,
			"path" : "generators/dvi/fontEncoding.cpp",
			"sourceGroupIndex" : 0
		},
		{
			"backtrace" : 3,
			"compileGroupIndex" : 0,
			"path" : "generators/dvi/fontEncodingPool.cpp",
			"sourceGroupIndex" : 0
		},
		{
			"backtrace" : 3,
			"compileGroupIndex" : 0,
			"path" : "generators/dvi/fontMap.cpp",
			"sourceGroupIndex" : 0
		},
		{
			"backtrace" : 3,
			"compileGroupIndex" : 0,
			"path" : "generators/dvi/fontpool.cpp",
			"sourceGroupIndex" : 0
		},
		{
			"backtrace" : 3,
			"compileGroupIndex" : 0,
			"path" : "generators/dvi/dvisourcesplitter.cpp",
			"sourceGroupIndex" : 0
		},
		{
			"backtrace" : 3,
			"compileGroupIndex" : 0,
			"path" : "generators/dvi/dviexport.cpp",
			"sourceGroupIndex" : 0
		}
	],
	"type" : "MODULE_LIBRARY"
}
